<?xml version="1.0" encoding="utf-8"?>
<!DOCTYPE GlossaryTerm >
<GlossaryTerm id="CDR0000372931"><TermName>meteorism</TermName><TermPronunciation>(MEE-tee-oh-rih-zum)</TermPronunciation><TermDefinition><DefinitionText>Swelling of the abdomen caused by gas in the intestines or peritoneal cavity. Also called tympanites.</DefinitionText><Dictionary>Cancer.gov</Dictionary><Audience>Patient</Audience></TermDefinition><MediaLink ref="CDR0000730839" type="audio/mpeg" alt="Pronunciation of dictionary term &quot;meteorism&quot;" language="en" id="_3"/><MediaLink ref="CDR0000730838" type="audio/mpeg" alt="Pronunciation of dictionary term &quot;meteorismo&quot;" language="es" id="_4"/><SpanishTermName>meteorismo</SpanishTermName><SpanishTermDefinition><DefinitionText>Hinchazón del abdomen causada por la presencia de gas en los intestinos o la cavidad peritoneal. También se llama timpanismo.</DefinitionText><Dictionary>Cancer.gov</Dictionary><Audience>Patient</Audience></SpanishTermDefinition><DateFirstPublished>2004-05-28</DateFirstPublished></GlossaryTerm>
