<?xml version="1.0" encoding="utf-8"?>
<!DOCTYPE GlossaryTerm >
<GlossaryTerm id="CDR0000346545"><TermName>CLL</TermName><TermDefinition><DefinitionText>An indolent (slow-growing) cancer in which too many immature lymphocytes (white blood cells) are found mostly in the blood and bone marrow. Sometimes, in later stages of the disease, cancer cells are found in the lymph nodes and the disease is called small lymphocytic lymphoma. Also called chronic lymphocytic leukemia.</DefinitionText><Dictionary>Cancer.gov</Dictionary><Audience>Patient</Audience></TermDefinition><SpanishTermName>LLC</SpanishTermName><SpanishTermDefinition><DefinitionText>Cáncer de crecimiento lento en el que se encuentran demasiados linfocitos inmaduros (glóbulos blancos) principalmente en la sangre y la médula ósea.   A veces, en los estadios posteriores de la enfermedad, las células cancerosas se encuentran en los ganglios linfáticos y la enfermedad se llama linfoma linfocítico pequeño.   También se llama leucemia linfocítica crónica.</DefinitionText><Dictionary>Cancer.gov</Dictionary><Audience>Patient</Audience></SpanishTermDefinition><DateFirstPublished>2003-11-20</DateFirstPublished><DateLastModified>2009-04-24</DateLastModified><RelatedInformation><RelatedExternalRef UseWith="en" xref="http://www.cancer.gov/types/leukemia">Leukemia</RelatedExternalRef><RelatedExternalRef UseWith="es" xref="http://www.cancer.gov/espanol/tipos/leucemia">Leucemia</RelatedExternalRef></RelatedInformation></GlossaryTerm>
