<?xml version="1.0" encoding="utf-8"?>
<!DOCTYPE GlossaryTerm >
<GlossaryTerm id="CDR0000416103"><TermName>stage II AIDS-related lymphoma</TermName><TermPronunciation>(... ree-LAY-ted lim-FOH-muh)</TermPronunciation><TermDefinition><DefinitionText>Stage II is divided into stages II and IIE. In stage II, cancer is found in two or more lymph node groups either above or below the diaphragm (the thin muscle below the lungs that helps breathing and separates the chest from the abdomen). In stage IIE, cancer is found in one or more lymph node groups either above or below the diaphragm. Cancer is also found outside the lymph nodes in one organ or area on the same side of the diaphragm as the affected lymph nodes.</DefinitionText><Dictionary>Cancer.gov</Dictionary><Audience>Patient</Audience></TermDefinition><MediaLink ref="CDR0000713445" type="audio/mpeg" alt="Pronunciation of dictionary term &quot;stage II AIDS-related lymphoma&quot;" language="en" id="_3"/><MediaLink ref="CDR0000713444" type="audio/mpeg" alt="Pronunciation of dictionary term &quot;linfoma relacionado con el SIDA en estadio II&quot;" language="es" id="_4"/><MediaLink ref="CDR0000737236" type="image/jpeg" alt="Stage II AIDS-related lymphoma; drawing shows cancer in lymph node groups above and below the diaphragm. An inset shows a lymph node with a lymph vessel, an artery, and a vein. Lymphoma cells containing cancer are shown in the lymph node." language="en" audience="Patients" thumb="Yes" id="_3"><Caption language="en">Stage II AIDS-related lymphoma. Cancer is found in two or more lymph node groups, and both are either above (a) or below (b) the diaphragm.</Caption></MediaLink><MediaLink ref="CDR0000737256" type="image/jpeg" alt="Stage IIE AIDS-related lymphoma; drawing shows cancer in one lymph node group above the diaphragm and in the left lung. An inset shows a lymph node with a lymph vessel, an artery, and a vein. Lymphoma cells containing cancer are shown in the lymph node." language="en" audience="Patients" thumb="Yes" id="_4"><Caption language="en">Stage IIE AIDS-related lymphoma. Cancer is found in one or more lymph node groups either above or below the diaphragm and outside the lymph nodes in an organ or area on the same side of the diaphragm as the lymph nodes with cancer (a).</Caption></MediaLink><MediaLink ref="CDR0000738321" type="image/jpeg" alt="Linfoma relacionado con el sida en estadio II; el dibujo muestra el cáncer en grupos de ganglios linfáticos por encima y debajo del diafragma. En un recuadro se observa un ganglio linfático con un vaso linfático, una arteria y una vena. En el ganglio linfático se ven las células de linfoma que contienen cáncer." language="es" audience="Patients" thumb="Yes" id="_5"><Caption language="es">Linfoma relacionado con el sida en estadio II. El cáncer se encuentra en dos o más grupos de ganglios linfáticos, y ambos están por encima (a) o debajo (b) del diafragma. </Caption></MediaLink><MediaLink ref="CDR0000738322" type="image/jpeg" alt="Linfoma relacionado con el sida en estadio IIE; el dibujo muestra el cáncer en un grupo de ganglios linfáticos por encima del diafragma y en el pulmón izquierdo. En un recuadro se observa un ganglio linfático con un vaso linfático, una arteria y una vena. En el ganglio linfático se observan las células de linfoma que contienen cáncer." language="es" audience="Patients" thumb="Yes" id="_6"><Caption language="es">Linfoma relacionado con el sida en estadio IIE. El cáncer se encuentra en uno o más grupos de ganglios linfáticos por encima o debajo del diafragma, y fuera de los ganglios linfáticos en un órgano o área del mismo lado del diafragma en el que están los ganglios linfáticos con cáncer (a).</Caption></MediaLink><SpanishTermName>linfoma relacionado con el SIDA en estadio II</SpanishTermName><SpanishTermDefinition><DefinitionText>El estadio II se divide en los estadios II y IIE. En el estadio II, el cáncer se encuentra en dos o más grupos de ganglios linfáticos por encima o debajo del diafragma (músculo delgado debajo de los pulmones que ayuda a respirar y separa el pecho del abdomen). En el estadio IIE, el cáncer se encuentra en uno o más grupos de ganglios linfáticos por encima o debajo del diafragma. El cáncer también se puede encontrar fuera de los ganglios linfáticos, en un área u órgano del mismo lado del diafragma que los ganglios linfáticos afectados.</DefinitionText><Dictionary>Cancer.gov</Dictionary><Audience>Patient</Audience></SpanishTermDefinition><DateFirstPublished>2005-04-23</DateFirstPublished><DateLastModified>2012-08-21</DateLastModified><RelatedInformation><RelatedSummaryRef UseWith="en" href="CDR0000257993">AIDS-Related Lymphoma Treatment</RelatedSummaryRef><RelatedSummaryRef UseWith="es" href="CDR0000420913">Linfoma relacionado con el sida: Tratamiento</RelatedSummaryRef></RelatedInformation></GlossaryTerm>
