<?xml version="1.0" encoding="utf-8"?>
<!DOCTYPE GlossaryTerm >
<GlossaryTerm id="CDR0000415915"><TermName>backbone</TermName><TermPronunciation>(BAK-bone)</TermPronunciation><TermDefinition><DefinitionText>The bones, muscles, tendons, and other tissues that reach from the base of the skull to the tailbone. The backbone encloses the spinal cord and the fluid surrounding the spinal cord. Also called spinal column, spine,  and vertebral column.</DefinitionText><Dictionary>Cancer.gov</Dictionary><Audience>Patient</Audience></TermDefinition><MediaLink ref="CDR0000733033" type="audio/mpeg" alt="Pronunciation of dictionary term &quot;backbone&quot;" language="en" id="_3"/><MediaLink ref="CDR0000733034" type="audio/mpeg" alt="Pronunciation of dictionary term &quot;espina dorsal&quot;" language="es" id="_4"/><SpanishTermName>espina dorsal</SpanishTermName><SpanishTermDefinition><DefinitionText>Los huesos, músculos, tendones y otros tejidos que van desde la base del cráneo hasta la rabadilla. La espina dorsal encierra la médula espinal y el líquido que rodea la médula espinal. También se llama columna espinal, columna vertebral,  y espina vertebral.</DefinitionText><Dictionary>Cancer.gov</Dictionary><Audience>Patient</Audience></SpanishTermDefinition><DateFirstPublished>2005-01-24</DateFirstPublished><DateLastModified>2008-11-21</DateLastModified></GlossaryTerm>
