<?xml version="1.0" encoding="utf-8"?>
<!DOCTYPE GlossaryTerm >
<GlossaryTerm id="CDR0000045254"><TermName>idarubicin hydrochloride</TermName><TermPronunciation>(I-duh-ROO-bih-sin HY-droh-KLOR-ide)</TermPronunciation><TermDefinition><DefinitionText>A drug used with other drugs to treat acute myelogenous leukemia (AML). It is also being studied in the treatment of other types of cancer. Idarubicin hydrochloride blocks a certain enzyme needed for cell division and DNA repair, and it may kill cancer cells. It is a type of anthracycline antibiotic and a type of topoisomerase inhibitor. Also called 4-demethoxydaunorubicin and Idamycin.</DefinitionText><Dictionary>Cancer.gov</Dictionary><Audience>Patient</Audience></TermDefinition><MediaLink ref="CDR0000705210" type="audio/mpeg" alt="Pronunciation of dictionary term &quot;idarubicin hydrochloride&quot;" language="en" id="_5"/><MediaLink ref="CDR0000705211" type="audio/mpeg" alt="Pronunciation of dictionary term &quot;clorhidrato de idarubicina&quot;" language="es" id="_6"/><SpanishTermName>clorhidrato de idarrubicina</SpanishTermName><SpanishTermDefinition><DefinitionText>Medicamento que se usa con otros para tratar la leucemia mielógena aguda (LMA). También está en estudio para el tratamiento de otros tipos de cáncer. El clorhidrato de idarrubicina bloquea cierta enzima necesaria para la multiplicación celular y la reparación del ADN; puede destruir células cancerosas. Es un tipo de antibiótico con antraciclina y un tipo de inhibidor de la topoisomerasa. También se llama 4-demetoxidaunorrubicina y Idamycin.</DefinitionText><Dictionary>Cancer.gov</Dictionary><Audience>Patient</Audience></SpanishTermDefinition><DateLastModified>2014-08-15</DateLastModified><RelatedInformation><RelatedDrugSummaryRef href="CDR0000762190">Idarubicin Hydrochloride</RelatedDrugSummaryRef></RelatedInformation></GlossaryTerm>
