<?xml version="1.0" encoding="utf-8"?>
<!DOCTYPE GlossaryTerm >
<GlossaryTerm id="CDR0000467825"><TermName>acupuncture point injection</TermName><TermPronunciation>(AK-yoo-PUNK-cher poynt in-JEK-shun)</TermPronunciation><TermDefinition><DefinitionText>A procedure in which drugs, vitamins, herbal extracts, or other fluids are injected into the body at an acupuncture point using a syringe and needle.</DefinitionText><Dictionary>Cancer.gov</Dictionary><Audience>Patient</Audience></TermDefinition><MediaLink ref="CDR0000717044" type="audio/mpeg" alt="Pronunciation of dictionary term &quot;acupuncture point injection&quot;" language="en" id="_3"/><MediaLink ref="CDR0000717045" type="audio/mpeg" alt="Pronunciation of dictionary term &quot;inyección en puntos de acupuntura&quot;" language="es" id="_4"/><SpanishTermName>inyección en puntos de acupuntura</SpanishTermName><SpanishTermDefinition><DefinitionText>Procedimiento por el que se inyectan medicamentos, vitaminas, extractos de hierbas u otros líquidos en el cuerpo en un punto de acupuntura, por medio de una jeringa y una aguja.</DefinitionText><Dictionary>Cancer.gov</Dictionary><Audience>Patient</Audience></SpanishTermDefinition><DateFirstPublished>2006-05-11</DateFirstPublished></GlossaryTerm>
