<?xml version="1.0" encoding="utf-8"?>
<!DOCTYPE GlossaryTerm >
<GlossaryTerm id="CDR0000044588"><TermName>enveloped virus</TermName><TermPronunciation>(EN-veh-lupt VY-rus)</TermPronunciation><TermDefinition><DefinitionText>A virus that has an outer wrapping or envelope. This envelope comes from the infected cell, or host, in a process called "budding off." During the budding process, newly formed virus particles become "enveloped" or wrapped in an outer coat that is made from a small piece of the cell's plasma membrane. The envelope may play a role in helping a virus survive and infect other cells.</DefinitionText><Dictionary>Cancer.gov</Dictionary><Audience>Patient</Audience></TermDefinition><MediaLink ref="CDR0000704809" type="audio/mpeg" alt="Pronunciation of dictionary term &quot;enveloped virus&quot;" language="en" id="_3"/><MediaLink ref="CDR0000704810" type="audio/mpeg" alt="Pronunciation of dictionary term &quot;virus envuelto&quot;" language="es" id="_4"/><SpanishTermName>virus envuelto</SpanishTermName><SpanishTermDefinition><DefinitionText>Virus que tiene una envoltura o capa exterior. Esta envoltura proviene de la célula infectada o del huésped, en un proceso llamado “gemación”. Durante el proceso de gemación, las partículas víricas recién formadas se “envuelven” o cubren con una capa externa formada por una pieza pequeña de la membrana plasmática de la célula. La envoltura puede cumplir la función de ayudar a un virus a sobrevivir e infectar a otras células.</DefinitionText><Dictionary>Cancer.gov</Dictionary><Audience>Patient</Audience></SpanishTermDefinition><DateLastModified>2007-03-08</DateLastModified></GlossaryTerm>
