<?xml version="1.0" encoding="utf-8"?>
<!DOCTYPE GlossaryTerm >
<GlossaryTerm id="CDR0000046393"><TermName>fulguration</TermName><TermPronunciation>(ful-guh-RAY-shun)</TermPronunciation><TermDefinition><DefinitionText>A procedure that uses heat from an electric current to destroy abnormal tissue, such as a tumor or other lesion. It may also be used to control bleeding during surgery or after an injury. The electric current passes through an electrode that is placed on or near the tissue. The tip of the electrode is heated by the electric current to burn or destroy the tissue.  Fulguration is a type of electrosurgery. Also called electrocautery, electrocoagulation,  and electrofulguration.</DefinitionText><Dictionary>Cancer.gov</Dictionary><Audience>Patient</Audience></TermDefinition><MediaLink ref="CDR0000708659" type="audio/mpeg" alt="Pronunciation of dictionary term &quot;fulguration&quot;" language="en" id="_3"/><MediaLink ref="CDR0000708660" type="audio/mpeg" alt="Pronunciation of dictionary term &quot;fulguración&quot;" language="es" id="_4"/><SpanishTermName>fulguración</SpanishTermName><SpanishTermDefinition><DefinitionText>Procedimiento que usa el calor de la corriente eléctrica para destruir tejido anormal, como los de un tumor u otra lesión. También se puede usar para controlar el sangrado  durante una operación quirúrgica o después de una lesión. La corriente eléctrica pasa por un electrodo que se coloca sobre el tejido o alrededor de este. La punta del electrodo se calienta mediante la corriente eléctrica para quemar o destruir el tejido.  es un tipo de electrocirugía. También se llama electrocauterización, electrocoagulación,  y electrofulguración.</DefinitionText><Dictionary>Cancer.gov</Dictionary><Audience>Patient</Audience></SpanishTermDefinition><DateLastModified>2013-07-16</DateLastModified></GlossaryTerm>
