<?xml version="1.0" encoding="utf-8"?>
<!DOCTYPE GlossaryTerm >
<GlossaryTerm id="CDR0000045537"><TermName>tocladesine</TermName><TermPronunciation>(toh-KLA-deh-seen)</TermPronunciation><TermDefinition><DefinitionText>A substance that has been studied as an anticancer drug. It is an analog of a substance that occurs naturally in the body (cyclic adenosine monophosphate).</DefinitionText><Dictionary>Cancer.gov</Dictionary><Audience>Patient</Audience></TermDefinition><MediaLink ref="CDR0000731071" type="audio/mpeg" alt="Pronunciation of dictionary term &quot;tocladesine&quot;" language="en" id="_3"/><MediaLink ref="CDR0000731070" type="audio/mpeg" alt="Pronunciation of dictionary term &quot;tocladesina&quot;" language="es" id="_4"/><SpanishTermName>tocladesina</SpanishTermName><SpanishTermDefinition><DefinitionText>Sustancia en estudio como medicamento contra el cáncer. Es un análogo de una sustancia que se presenta naturalmente en el cuerpo (monofosfato cíclico de adenosina).</DefinitionText><Dictionary>Cancer.gov</Dictionary><Audience>Patient</Audience></SpanishTermDefinition><DateLastModified>2005-05-16</DateLastModified></GlossaryTerm>
