<?xml version="1.0" encoding="utf-8"?>
<!DOCTYPE GlossaryTerm >
<GlossaryTerm id="CDR0000046025"><TermName>nasopharynx</TermName><TermPronunciation>(NAY-zoh-FAYR-inx)</TermPronunciation><TermDefinition><DefinitionText>The upper part of the throat behind the nose. An opening on each side of the nasopharynx leads into the ear.</DefinitionText><Dictionary>Cancer.gov</Dictionary><Audience>Patient</Audience></TermDefinition><MediaLink ref="CDR0000708033" type="audio/mpeg" alt="Pronunciation of dictionary term &quot;nasopharynx&quot;" language="en" id="_3"/><MediaLink ref="CDR0000708034" type="audio/mpeg" alt="Pronunciation of dictionary term &quot;nasofaringe&quot;" language="es" id="_4"/><MediaLink ref="CDR0000713970" type="image/jpeg" alt="Anatomy of the pharynx; drawing shows the nasopharynx, oropharynx, and hypopharynx. Also shown are the nasal cavity, oral cavity, esophagus, trachea, and larynx." language="en" audience="Patients" thumb="Yes" id="_3"><Caption language="en">Anatomy of the pharynx (throat). The three parts of the pharynx are the nasopharynx, oropharynx,  and hypopharynx.</Caption></MediaLink><MediaLink ref="CDR0000732292" type="image/jpeg" alt="Anatomía de la faringe; el dibujo muestra la nasofaringe, la orofaringe y la hipofaringe. También se muestran la cavidad nasal, la cavidad oral, el esófago, la tráquea y la laringe." language="es" audience="Patients" thumb="Yes" id="_4"><Caption language="es">Anatomía de la faringe (garganta). Las tres partes de la faringe son la nasofaringe, la orofaringe y la hipofaringe.</Caption></MediaLink><SpanishTermName>nasofaringe</SpanishTermName><SpanishTermDefinition><DefinitionText>Parte superior de la garganta detrás de la nariz. Una abertura en cada lado de la nasofaringe conduce al oído.</DefinitionText><Dictionary>Cancer.gov</Dictionary><Audience>Patient</Audience></SpanishTermDefinition><DateLastModified>2014-10-28</DateLastModified><RelatedInformation><RelatedSummaryRef UseWith="en" href="CDR0000062966">Nasopharyngeal Cancer Treatment</RelatedSummaryRef><RelatedSummaryRef UseWith="es" href="CDR0000256817">Cáncer de nasofaringe: Tratamiento</RelatedSummaryRef></RelatedInformation></GlossaryTerm>
