<?xml version="1.0" encoding="utf-8"?>
<!DOCTYPE GlossaryTerm >
<GlossaryTerm id="CDR0000045124"><TermName>stage III bladder cancer</TermName><TermPronunciation>(... BLA-der KAN-ser)</TermPronunciation><TermDefinition><DefinitionText>Cancer has spread from the bladder to the layer of fat surrounding it and may have spread to the reproductive organs (prostate, seminal vesicles, uterus, or vagina).</DefinitionText><Dictionary>Cancer.gov</Dictionary><Audience>Patient</Audience></TermDefinition><MediaLink ref="CDR0000705035" type="audio/mpeg" alt="Pronunciation of dictionary term &quot;stage III bladder cancer&quot;" language="en" id="_3"/><MediaLink ref="CDR0000705034" type="audio/mpeg" alt="Pronunciation of dictionary term &quot;cáncer de vejiga en estadio III&quot;" language="es" id="_4"/><MediaLink ref="CDR0000749310" type="image/jpeg" alt="Stage III bladder cancer; drawing shows the bladder, ureter, prostate, and urethra. Inset shows cancer in the inner lining of the bladder, the layer of connective tissue, the muscle layers, and the layer of fat around the bladder." language="en" audience="Patients" thumb="Yes" id="_3"><Caption language="en">Stage III bladder cancer. Cancer has spread from the bladder to the layer of fat surrounding it. It may also have spread to the prostate and/or seminal vesicles in men or the uterus and/or vagina in women.</Caption></MediaLink><MediaLink ref="CDR0000752482" type="image/jpeg" alt="Cáncer de vejiga en estadio lll; el dibujo muestra la vejiga, el uréter, la próstata, y la uretra. El recuadro muestra el cáncer en el revestimiento interno de la vejiga, la capa de tejido conjuntivo, las capas musculares, y la capa de grasa alrededor de la vejiga." language="es" audience="Patients" thumb="Yes" id="_4"><Caption language="es">Cáncer de vejiga en estadio lll. El cáncer se diseminó desde la vejiga hasta la capa de grasa que la rodea. También se pudo haber diseminado a la próstata o las vesículas seminales en los hombres o al útero o la vagina en las mujeres.</Caption></MediaLink><SpanishTermName>cáncer de vejiga en estadio III</SpanishTermName><SpanishTermDefinition><DefinitionText>El cáncer se diseminó desde la
vejiga hasta la capa de grasa que la rodea y se
puede haber diseminado hasta los órganos reproductores
(próstata, vesículas seminales, útero o
vagina).</DefinitionText><Dictionary>Cancer.gov</Dictionary><Audience>Patient</Audience></SpanishTermDefinition><DateLastModified>2013-09-25</DateLastModified><RelatedInformation><RelatedSummaryRef UseWith="en" href="CDR0000062705">Bladder Cancer Treatment</RelatedSummaryRef><RelatedSummaryRef UseWith="es" href="CDR0000256808">Cáncer de vejiga: Tratamiento</RelatedSummaryRef></RelatedInformation></GlossaryTerm>
