<?xml version="1.0" encoding="utf-8"?>
<!DOCTYPE GlossaryTerm >
<GlossaryTerm id="CDR0000046573"><TermName>scrotum</TermName><TermPronunciation>(SKROH-tum)</TermPronunciation><TermDefinition><DefinitionText>In males, the external sac that contains the testicles.</DefinitionText><Dictionary>Cancer.gov</Dictionary><Audience>Patient</Audience></TermDefinition><MediaLink ref="CDR0000708965" type="audio/mpeg" alt="Pronunciation of dictionary term &quot;scrotum&quot;" language="en" id="_3"/><MediaLink ref="CDR0000708966" type="audio/mpeg" alt="Pronunciation of dictionary term &quot;escroto&quot;" language="es" id="_4"/><SpanishTermName>escroto</SpanishTermName><SpanishTermDefinition><DefinitionText>En los varones, la bolsa externa que contiene los testículos.</DefinitionText><Dictionary>Cancer.gov</Dictionary><Audience>Patient</Audience></SpanishTermDefinition></GlossaryTerm>
