<?xml version="1.0" encoding="utf-8"?>
<!DOCTYPE GlossaryTerm >
<GlossaryTerm id="CDR0000463167"><TermName>pharmacology</TermName><TermPronunciation>(FAR-muh-KAH-loh-jee)</TermPronunciation><TermDefinition><DefinitionText>The study of the origin, chemistry, and uses of drugs and their effects on the body.</DefinitionText><Dictionary>Cancer.gov</Dictionary><Audience>Patient</Audience></TermDefinition><MediaLink ref="CDR0000716975" type="audio/mpeg" alt="Pronunciation of dictionary term &quot;pharmacology&quot;" language="en" id="_3"/><MediaLink ref="CDR0000716974" type="audio/mpeg" alt="Pronunciation of dictionary term &quot;farmacología&quot;" language="es" id="_4"/><SpanishTermName>farmacología</SpanishTermName><SpanishTermDefinition><DefinitionText>Estudio del origen, las propiedades químicas y los usos de los medicamentos, así como de sus efectos en el cuerpo.</DefinitionText><Dictionary>Cancer.gov</Dictionary><Audience>Patient</Audience></SpanishTermDefinition><DateFirstPublished>2006-09-10</DateFirstPublished></GlossaryTerm>
