<?xml version="1.0" encoding="utf-8"?>
<!DOCTYPE GlossaryTerm >
<GlossaryTerm id="CDR0000045358"><TermName>theophylline</TermName><TermPronunciation>(thee-AH-fih-lin)</TermPronunciation><TermDefinition><DefinitionText>A drug used to improve breathing in people who are short of breath. It belongs to the family of drugs called bronchodilators or respiratory smooth muscle relaxants.</DefinitionText><Dictionary>Cancer.gov</Dictionary><Audience>Patient</Audience></TermDefinition><MediaLink ref="CDR0000730903" type="audio/mpeg" alt="Pronunciation of dictionary term &quot;theophylline&quot;" language="en" id="_3"/><MediaLink ref="CDR0000730902" type="audio/mpeg" alt="Pronunciation of dictionary term &quot;teofilina&quot;" language="es" id="_4"/><SpanishTermName>teofilina</SpanishTermName><SpanishTermDefinition><DefinitionText>Medicamento usado para mejorar la respiración de las personas que les falta el aliento. Es un tipo de broncodilatador o relajante de los músculo respiratorios lisos.</DefinitionText><Dictionary>Cancer.gov</Dictionary><Audience>Patient</Audience></SpanishTermDefinition></GlossaryTerm>
