<?xml version="1.0" encoding="utf-8"?>
<!DOCTYPE GlossaryTerm >
<GlossaryTerm id="CDR0000441265"><TermName>spirituality</TermName><TermPronunciation>(SPEER-ih-choo-A-lih-tee)</TermPronunciation><TermDefinition><DefinitionText>Having to do with deep, often religious, feelings and beliefs, including a person’s sense of peace, purpose, connection to others, and beliefs about the meaning of life.</DefinitionText><Dictionary>Cancer.gov</Dictionary><Audience>Patient</Audience></TermDefinition><MediaLink ref="CDR0000713754" type="audio/mpeg" alt="Pronunciation of dictionary term &quot;spirituality&quot;" language="en" id="_3"/><MediaLink ref="CDR0000713755" type="audio/mpeg" alt="Pronunciation of dictionary term &quot;espiritualidad&quot;" language="es" id="_4"/><SpanishTermName>espiritualidad</SpanishTermName><SpanishTermDefinition><DefinitionText>Relacionado con sentimientos y creencias profundas, a menudo religiosas, como la sensación de paz de una persona, su propósito en la vida, la relación con los otros y las creencias acerca del sentido de la vida.</DefinitionText><Dictionary>Cancer.gov</Dictionary><Audience>Patient</Audience></SpanishTermDefinition><DateFirstPublished>2005-10-24</DateFirstPublished><RelatedInformation><RelatedSummaryRef UseWith="en" href="CDR0000301599">Spirituality in Cancer Care</RelatedSummaryRef><RelatedSummaryRef UseWith="es" href="CDR0000334873">La espiritualidad en el tratamiento del cáncer</RelatedSummaryRef></RelatedInformation></GlossaryTerm>
