<?xml version="1.0" encoding="utf-8"?>
<!DOCTYPE GlossaryTerm >
<GlossaryTerm id="CDR0000046041"><TermName>neuropathy</TermName><TermPronunciation>(noor-AH-puh-thee)</TermPronunciation><TermDefinition><DefinitionText>A nerve problem that causes pain, numbness, tingling, swelling, or muscle weakness in different parts of the body. It usually begins in the hands or feet and gets worse over time. Neuropathy may be caused by cancer or cancer treatment, such as chemotherapy. It may also be caused by physical injury, infection, toxic substances, or conditions such as diabetes, kidney failure, or malnutrition. Also called peripheral neuropathy.</DefinitionText><Dictionary>Cancer.gov</Dictionary><Audience>Patient</Audience></TermDefinition><MediaLink ref="CDR0000708056" type="audio/mpeg" alt="Pronunciation of dictionary term &quot;neuropathy&quot;" language="en" id="_3"/><MediaLink ref="CDR0000708055" type="audio/mpeg" alt="Pronunciation of dictionary term &quot;neuropatía&quot;" language="es" id="_4"/><SpanishTermName>neuropatía</SpanishTermName><SpanishTermDefinition><DefinitionText>Problema de los nervios que produce dolor, adormecimiento, cosquilleo, hinchazón y debilidad muscular en distintas partes del cuerpo. Por lo general, comienza en las manos o los pies y empeora con el tiempo. El cáncer o su tratamiento, como la quimioterapia, pueden causar neuropatía. También pueden causarla las lesiones físicas, las infecciones, las sustancias tóxicas o las afecciones como diabetes, insuficiencia de los riñones o desnutrición. También se llama neuropatía periférica.</DefinitionText><Dictionary>Cancer.gov</Dictionary><Audience>Patient</Audience></SpanishTermDefinition><DateLastModified>2013-08-30</DateLastModified><RelatedInformation><RelatedExternalRef UseWith="en" xref="http://www.cancer.gov/publications/patient-education/nerve.pdf">Managing Chemotherapy Side Effects: Nerve Changes</RelatedExternalRef><RelatedExternalRef UseWith="es" xref="http://www.cancer.gov/espanol/publicaciones/educacion-para-pacientes/sp-chemosheets-cambios-nervios.pdf">Consejos para los efectos de la quimioterapia: Cambios en los nervios</RelatedExternalRef></RelatedInformation></GlossaryTerm>
