<?xml version="1.0" encoding="utf-8"?>
<!DOCTYPE GlossaryTerm >
<GlossaryTerm id="CDR0000044383"><TermName>N-acetyldinaline</TermName><TermPronunciation>(… A-seh-til-dih-nuh-leen)</TermPronunciation><TermDefinition><DefinitionText>A substance that is being studied as an anticancer drug in the treatment of non-small cell lung cancer. Also called CI-994.</DefinitionText><Dictionary>Cancer.gov</Dictionary><Audience>Patient</Audience></TermDefinition><MediaLink ref="CDR0000727940" type="audio/mpeg" alt="Pronunciation of dictionary term &quot;N-acetyldinaline&quot;" language="en" id="_3"/><MediaLink ref="CDR0000727939" type="audio/mpeg" alt="Pronunciation of dictionary term &quot;N-acetildinalina&quot;" language="es" id="_4"/><SpanishTermName>N-acetildinalina</SpanishTermName><SpanishTermDefinition><DefinitionText>Sustancia en estudio para el tratamiento del cáncer de pulmón de células no pequeñas. También se llama CI-994.</DefinitionText><Dictionary>Cancer.gov</Dictionary><Audience>Patient</Audience></SpanishTermDefinition><DateLastModified>2007-06-29</DateLastModified></GlossaryTerm>
