<?xml version="1.0" encoding="utf-8"?>
<!DOCTYPE GlossaryTerm >
<GlossaryTerm id="CDR0000557355"><TermName>spinal cord compression</TermName><TermPronunciation>(SPY-nul kord kum-PREH-shun)</TermPronunciation><TermDefinition><DefinitionText>Pressure on the spinal cord that may be caused by a tumor, a spinal fracture, or other conditions. Spinal cord compression may cause pain, weakness, loss of feeling, paralysis, incontinence (inability to control urine or stool), or impotence (inability to have an erection of the penis).</DefinitionText><Dictionary>Cancer.gov</Dictionary><Audience>Patient</Audience></TermDefinition><MediaLink ref="CDR0000720559" type="audio/mpeg" alt="Pronunciation of dictionary term &quot;spinal cord compression&quot;" language="en" id="_3"/><MediaLink ref="CDR0000720560" type="audio/mpeg" alt="Pronunciation of dictionary term &quot;compresión de la médula espinal&quot;" language="es" id="_4"/><SpanishTermName>compresión de la médula espinal</SpanishTermName><SpanishTermDefinition><DefinitionText>Presión en la médula espinal que puede obedecer a un tumor, una fractura en la columna vertebral u otras afecciones. La compresión de la médula espinal puede causar dolor, debilidad, pérdida de sensibilidad, parálisis, incontinencia (incapacidad de controlar la orina o las materias fecales) o impotencia (incapacidad de tener una erección del pene).</DefinitionText><Dictionary>Cancer.gov</Dictionary><Audience>Patient</Audience></SpanishTermDefinition><DateFirstPublished>2008-03-10</DateFirstPublished></GlossaryTerm>
