<?xml version="1.0" encoding="utf-8"?>
<!DOCTYPE GlossaryTerm >
<GlossaryTerm id="CDR0000655061"><TermName>vitamin D2</TermName><TermPronunciation>(VY-tuh-min …)</TermPronunciation><TermDefinition><DefinitionText>A form of vitamin D that helps the body use calcium and phosphorus to make strong bones and teeth. It is fat-soluble (can dissolve in fats and oils) and is found in plants and yeast. It can be made in the body from another form of vitamin D when the body is exposed to the sun. Vitamin D2 is also made in the laboratory. It is used to prevent and to treat vitamin D deficiency. It is a type of dietary supplement. Also called ergocalciferol.</DefinitionText><Dictionary>Cancer.gov</Dictionary><Audience>Patient</Audience></TermDefinition><MediaLink ref="CDR0000726353" type="audio/mpeg" alt="Pronunciation of dictionary term &quot;vitamin D2&quot;" language="en" id="_3"/><MediaLink ref="CDR0000726352" type="audio/mpeg" alt="Pronunciation of dictionary term &quot;vitamina D2&quot;" language="es" id="_4"/><SpanishTermName>vitamina D2</SpanishTermName><SpanishTermDefinition><DefinitionText>Forma de vitamina D que ayuda al organismo a usar el calcio y el fósforo para lograr huesos y dientes fuertes. Es soluble en grasa (se disuelve en grasas y aceites) y se encuentra en plantas y levaduras. Se puede producir en el cuerpo a partir de otras formas de vitamina D cuando el cuerpo se expone al sol. La vitamina D2 también se produce en el laboratorio. Se usa para prevenir y tratar la deficiencia de vitamina D. Es un tipo de suplemento alimentario. También se llama ergocalciferol.</DefinitionText><Dictionary>Cancer.gov</Dictionary><Audience>Patient</Audience></SpanishTermDefinition><DateFirstPublished>2009-11-17</DateFirstPublished></GlossaryTerm>
