<?xml version="1.0" encoding="utf-8"?>
<!DOCTYPE GlossaryTerm >
<GlossaryTerm id="CDR0000653117"><TermName>immunohistochemistry</TermName><TermPronunciation>(IH-myoo-noh-HIS-toh-KEH-mih-stree)</TermPronunciation><TermDefinition><DefinitionText>A laboratory test that uses antibodies to test for certain antigens in a sample of tissue. The antibody is usually linked to a radioactive substance or a dye that causes the antigens in the tissue to light up under a microscope. Immunohistochemistry is used to help diagnose diseases, such as cancer. It may also be used to help tell the difference between different types of cancer.</DefinitionText><Dictionary>Cancer.gov</Dictionary><Audience>Patient</Audience></TermDefinition><MediaLink ref="CDR0000726441" type="audio/mpeg" alt="Pronunciation of dictionary term &quot;immunohistochemistry&quot;" language="en" id="_3"/><MediaLink ref="CDR0000726442" type="audio/mpeg" alt="Pronunciation of dictionary term &quot;inmunohistoquímica&quot;" language="es" id="_4"/><SpanishTermName>inmunohistoquímica</SpanishTermName><SpanishTermDefinition><DefinitionText>Prueba de laboratorio para la que se usan anticuerpos para identificar ciertos antígenos en una muestra de tejido. Por lo general, el anticuerpo se une a una sustancia radiactiva o un tinte que hace que los antígenos en el tejido se iluminen al microscopio. La inmunohistoquímica se usa para ayudar a diagnosticar enfermedades como el cáncer. También se puede usar para ayudar a distinguir entre diferentes tipos de cáncer.</DefinitionText><Dictionary>Cancer.gov</Dictionary><Audience>Patient</Audience></SpanishTermDefinition><DateFirstPublished>2009-09-30</DateFirstPublished><DateLastModified>2014-03-25</DateLastModified></GlossaryTerm>
